databaker/__init__.py
databaker/constants.py
databaker/databaker_nbconvert.py
databaker/framework.py
databaker/jupybakecsv.py
databaker/jupybakehtml.py
databaker/jupybakeutils.py
databaker/overrides.py
databaker/structure_csv_default.py
databaker/tutorial.py
databaker/richxlrd/__init__.py
databaker/richxlrd/richxlrd.py
databaker-2.0.0.dist-info/DESCRIPTION.rst
databaker-2.0.0.dist-info/METADATA
databaker-2.0.0.dist-info/RECORD
databaker-2.0.0.dist-info/WHEEL
databaker-2.0.0.dist-info/entry_points.txt
databaker-2.0.0.dist-info/metadata.json
databaker-2.0.0.dist-info/namespace_packages.txt
databaker-2.0.0.dist-info/top_level.txt
