Metadata-Version: 2.0
Name: databaker
Version: 2.0.0
Summary: DataBaker, part of QuickCode for ONS
Home-page: https://github.com/sensiblecodeio/databaker
Author: The Sensible Code Company Ltd
Author-email: feedback@sensiblecode.io
License: AGPL
Platform: UNKNOWN
Classifier: Development Status :: 3 - Alpha
Classifier: License :: OSI Approved :: GNU Affero General Public License v3 or later (AGPLv3+)
Classifier: Operating System :: POSIX :: Linux
Classifier: Operating System :: Microsoft :: Windows
Classifier: Programming Language :: Python :: 3.4
Classifier: Programming Language :: Python :: 3.5
Classifier: Programming Language :: Python :: 3.6
Requires-Dist: docopt
Requires-Dist: pyhamcrest
Requires-Dist: xlutils
Requires-Dist: xypath (>=1.1.0)
